rollbar/__init__.py
rollbar/cli.py
rollbar/logger.py
rollbar/contrib/__init__.py
rollbar/contrib/asgi/__init__.py
rollbar/contrib/asgi/integration.py
rollbar/contrib/asgi/middleware.py
rollbar/contrib/asgi/types.py
rollbar/contrib/bottle/__init__.py
rollbar/contrib/django/__init__.py
rollbar/contrib/django/context_processors.py
rollbar/contrib/django/middleware.py
rollbar/contrib/django/models.py
rollbar/contrib/django/tests.py
rollbar/contrib/django/utils.py
rollbar/contrib/django_rest_framework/__init__.py
rollbar/contrib/fastapi/__init__.py
rollbar/contrib/fastapi/logger.py
rollbar/contrib/fastapi/middleware.py
rollbar/contrib/fastapi/routing.py
rollbar/contrib/fastapi/utils.py
rollbar/contrib/flask/__init__.py
rollbar/contrib/pyramid/__init__.py
rollbar/contrib/quart/__init__.py
rollbar/contrib/rq/__init__.py
rollbar/contrib/starlette/__init__.py
rollbar/contrib/starlette/logger.py
rollbar/contrib/starlette/middleware.py
rollbar/contrib/starlette/requests.py
rollbar/examples/asgi/app.py
rollbar/examples/django/app.py
rollbar/examples/fastapi/app.py
rollbar/examples/fastapi/app_global_request.py
rollbar/examples/fastapi/app_logger.py
rollbar/examples/fastapi/app_middleware.py
rollbar/examples/flask/app.py
rollbar/examples/starlette/app.py
rollbar/examples/starlette/app_global_request.py
rollbar/examples/starlette/app_logger.py
rollbar/examples/twisted/simpleserv.py
rollbar/lib/__init__.py
rollbar/lib/_async.py
rollbar/lib/events.py
rollbar/lib/thread_pool.py
rollbar/lib/transform.py
rollbar/lib/transport.py
rollbar/lib/traverse.py
rollbar/lib/type_info.py
rollbar/lib/filters/__init__.py
rollbar/lib/filters/basic.py
rollbar/lib/transforms/__init__.py
rollbar/lib/transforms/batched.py
rollbar/lib/transforms/scrub.py
rollbar/lib/transforms/scrub_redact.py
rollbar/lib/transforms/scruburl.py
rollbar/lib/transforms/serializable.py
rollbar/lib/transforms/shortener.py
rollbar/test/__init__.py
rollbar/test/test_basic_filters.py
rollbar/test/test_batched_transform.py
rollbar-1.1.2.dist-info/LICENSE
rollbar-1.1.2.dist-info/METADATA
rollbar-1.1.2.dist-info/WHEEL
rollbar-1.1.2.dist-info/entry_points.txt
rollbar-1.1.2.dist-info/top_level.txt
rollbar-1.1.2.dist-info/RECORD
