Metadata-Version: 2.2
Name: rollbar
Version: 1.1.2
Summary: Easy and powerful exception tracking with Rollbar. Send messages and exceptions with arbitrary context, get back aggregates, and debug production issues quickly.
Maintainer-email: "Rollbar, Inc." <support@rollbar.com>
License: Copyright (c) 2014 Rollbar, Inc.
Project-URL: Homepage, https://rollbar.com/
Project-URL: Documentation, https://docs.rollbar.com/docs/python
Project-URL: Changes, https://github.com/rollbar/pyrollbar/blob/master/CHANGELOG.md
Project-URL: Source, https://github.com/rollbar/pyrollbar/
Classifier: Programming Language :: Python
Classifier: Programming Language :: Python :: 3
Classifier: Programming Language :: Python :: 3.6
Classifier: Programming Language :: Python :: 3.7
Classifier: Programming Language :: Python :: 3.8
Classifier: Programming Language :: Python :: 3.9
Classifier: Programming Language :: Python :: 3.10
Classifier: Programming Language :: Python :: 3.11
Classifier: Programming Language :: Python :: 3.12
Classifier: Programming Language :: Python :: 3 :: Only
Classifier: License :: OSI Approved :: MIT License
Classifier: Operating System :: OS Independent
Classifier: Development Status :: 5 - Production/Stable
Classifier: Environment :: Web Environment
Classifier: Framework :: AsyncIO
Classifier: Framework :: Bottle
Classifier: Framework :: Django
Classifier: Framework :: Flask
Classifier: Framework :: Pylons
Classifier: Framework :: Pyramid
Classifier: Framework :: Twisted
Classifier: Intended Audience :: Developers
Classifier: Topic :: Internet :: WWW/HTTP
Classifier: Topic :: Software Development
Classifier: Topic :: Software Development :: Bug Tracking
Classifier: Topic :: Software Development :: Testing
Classifier: Topic :: Software Development :: Quality Assurance
Classifier: Topic :: System :: Logging
Classifier: Topic :: System :: Monitoring
Requires-Python: >=3.6
License-File: LICENSE
Requires-Dist: requests>=0.12.1
